cleopy/__init__.py
cleopy/cxx2py.py
cleopy/editconfigfile.py
cleopy/geninitconds.py
cleopy/readbinary.py
cleopy/readconfigfile.py
cleopy/writebinary.py
cleopy/gbxboundariesbinary_src/__init__.py
cleopy/gbxboundariesbinary_src/create_gbxboundaries.py
cleopy/gbxboundariesbinary_src/read_gbxboundaries.py
cleopy/initsuperdropsbinary_src/__init__.py
cleopy/initsuperdropsbinary_src/attrsgen.py
cleopy/initsuperdropsbinary_src/crdgens.py
cleopy/initsuperdropsbinary_src/create_initsuperdrops.py
cleopy/initsuperdropsbinary_src/dryrgens.py
cleopy/initsuperdropsbinary_src/probdists.py
cleopy/initsuperdropsbinary_src/read_initsuperdrops.py
cleopy/initsuperdropsbinary_src/rgens.py
cleopy/sdmout_src/__init__.py
cleopy/sdmout_src/massmoms.py
cleopy/sdmout_src/pygbxsdat.py
cleopy/sdmout_src/pysetuptxt.py
cleopy/sdmout_src/pyzarr.py
cleopy/sdmout_src/sdtracing.py
cleopy/sdmout_src/superdrops.py
cleopy/sdmout_src/supersdata.py
cleopy/sdmout_src/thermodata.py
cleopy/sdmout_src/thermoeqns.py
cleopy/sdmout_src/timedata.py
cleopy/thermobinary_src/__init__.py
cleopy/thermobinary_src/create_thermodynamics.py
cleopy/thermobinary_src/read_thermodynamics.py
cleopy/thermobinary_src/thermodyngen.py
cleopy/thermobinary_src/thermogen.py
cleopy/thermobinary_src/windsgen.py
cleopy-0.64.0.dist-info/METADATA
cleopy-0.64.0.dist-info/WHEEL
cleopy-0.64.0.dist-info/licenses/LICENSE.md
cleopy-0.64.0.dist-info/RECORD
