Metadata-Version: 2.4
Name: cleopy
Version: 0.64.0
Summary: Python package for generating input and processing output of CLEO SDM
Project-URL: Homepage, https://github.com/yoctoyotta1024/CLEO
Project-URL: Website, https://yoctoyotta1024.github.io/CLEO
Project-URL: Issues, https://github.com/yoctoyotta1024/CLEO/issues
Author-email: Clara Bayley <yoctoyotta1024@yahoo.com>
License-Expression: BSD-3-Clause
License-File: LICENSE.md
Requires-Python: >=3.13
Requires-Dist: awkward
Requires-Dist: matplotlib
Requires-Dist: numpy
Requires-Dist: ruamel-yaml
Requires-Dist: scipy
Requires-Dist: xarray
Requires-Dist: zarr
Provides-Extra: examples
Requires-Dist: mpi4py; extra == 'examples'
Provides-Extra: yac
Requires-Dist: cython; extra == 'yac'
Requires-Dist: datetime; extra == 'yac'
Requires-Dist: isodate; extra == 'yac'
Requires-Dist: mpi4py; extra == 'yac'
Requires-Dist: netcdf4; extra == 'yac'
